shpinfo-0.2.0.dist-info/WHEEL
shpinfo-0.2.0.dist-info/RECORD
shpinfo-0.2.0.dist-info/metadata.json
shpinfo-0.2.0.dist-info/entry_points.txt
shpinfo-0.2.0.dist-info/METADATA
shpinfo-0.2.0.dist-info/top_level.txt
shpinfo-0.2.0.dist-info/DESCRIPTION.rst
shpinfo/__init__.py
shpinfo/shpinfo.py
