Metadata-Version: 2.0
Name: shpinfo
Version: 0.2.0
Summary: A command line program to print meta information about the given shapefile.
Home-page: https://github.com/yaph/shpinfo
Author: Ramiro Gómez
Author-email: code@ramiro.org
License: MIT
Keywords: gis geospatial geography shapefile
Platform: UNKNOWN
Classifier: Development Status :: 4 - Beta
Classifier: Intended Audience :: Developers
Classifier: License :: OSI Approved :: BSD License
Classifier: Natural Language :: English
Classifier: Programming Language :: Python :: 2
Classifier: Programming Language :: Python :: 2.7
Classifier: Programming Language :: Python :: 3
Classifier: Programming Language :: Python :: 3.3
Classifier: Programming Language :: Python :: 3.4
Requires-Dist: click (==4.0)
Requires-Dist: pyshp (==1.2.3)
